phantominator/__init__.py
phantominator/ct_shepp_logan.py
phantominator/dynamic.py
phantominator/kspace.py
phantominator/mr_shepp_logan.py
phantominator/sens_coeffs.py
phantominator/shepp_logan.py
phantominator/traj.py
phantominator/examples/__init__.py
phantominator/examples/dynamic.py
phantominator/examples/gach_figs.py
phantominator/examples/modify_parameters.py
phantominator/examples/mr_shepp_logan.py
phantominator/examples/radial_coil_sens.py
phantominator/examples/shepp_logan.py
phantominator-0.7.0.dist-info/LICENSE
phantominator-0.7.0.dist-info/METADATA
phantominator-0.7.0.dist-info/WHEEL
phantominator-0.7.0.dist-info/top_level.txt
phantominator-0.7.0.dist-info/RECORD
