Metadata-Version: 2.1
Name: phantominator
Version: 0.7.0
Summary: Generate numerical phantoms.
Home-page: https://github.com/mckib2/phantominator
Author: Nicholas McKibben
Author-email: nicholas.bgp@gmail.com
License: MIT
Requires-Python: >=3.8
License-File: LICENSE
Requires-Dist: numpy (>=1.24.2)
Requires-Dist: scipy (>=1.9.1)
Requires-Dist: matplotlib (>=3.7.1)
Requires-Dist: ssfp (>=1.0.0)
